src/__init__.py
src/script.py
cctx_importer-0.1.0.dist-info/WHEEL
cctx_importer-0.1.0.dist-info/entry_points.txt
cctx_importer-0.1.0.dist-info/METADATA
cctx_importer-0.1.0.dist-info/RECORD
