Metadata-Version: 2.3
Name: cctx-importer
Version: 0.1.0
Summary: Import Claude context profiles from configs directory
Author: Leynier Gutiérrez González
Author-email: Leynier Gutiérrez González <leynier41@gmail.com>
Requires-Dist: typer[all]>=0.21.1
Requires-Python: >=3.13
